cast_control/__init__.py
cast_control/__main__.py
cast_control/adapter.py
cast_control/base.py
cast_control/cli.py
cast_control/daemon.py
cast_control/listeners.py
cast_control/run.py
cast_control/types.py
cast_control/wrapper.py
cast_control/assets/template.desktop
cast_control/assets/icon/cc-black.png
cast_control/assets/icon/cc-white.png
chromecast_mpris/__init__.py
chromecast_mpris/__main__.py
chromecast_mpris/adapter.py
chromecast_mpris/base.py
chromecast_mpris/command.py
chromecast_mpris/listeners.py
chromecast_mpris/run.py
chromecast_mpris/wrapper.py
chromecast_mpris/assets/chromecast_mpris.desktop
chromecast_mpris/assets/icon/cc-black.png
chromecast_mpris/assets/icon/cc-white.png
chromecast_mpris-0.8.12.dist-info/LICENSE
chromecast_mpris-0.8.12.dist-info/METADATA
chromecast_mpris-0.8.12.dist-info/WHEEL
chromecast_mpris-0.8.12.dist-info/entry_points.txt
chromecast_mpris-0.8.12.dist-info/top_level.txt
chromecast_mpris-0.8.12.dist-info/zip-safe
chromecast_mpris-0.8.12.dist-info/RECORD
