Metadata-Version: 2.1
Name: chromecast-mpris
Version: 0.8.12
Summary: 📺 Control Chromecasts from Linux and D-Bus
Home-page: https://github.com/alexdelorenzo/chromecast_mpris
Author: Alex DeLorenzo
License: AGPL-3.0
Platform: UNKNOWN
Requires-Python: >=3.6
Requires-Dist: appdirs (>=1.4.4)
Requires-Dist: click (>=8.0.1)
Requires-Dist: PyChromecast (>=9.2.0)
Requires-Dist: pydbus (>=0.6.0)
Requires-Dist: PyGObject (>=3.34.0)
Requires-Dist: mpris-server (>=0.2.18)
Requires-Dist: cast-control (>=0.10.9) ; python_version >= "3.7"
